izi_pygame/__init__.py
izi_pygame/block.py
izi_pygame/izipygame.py
izi_pygame/police.py
izi_pygame/window.py
izi_pygame-0.1.9.dist-info/METADATA
izi_pygame-0.1.9.dist-info/RECORD
izi_pygame-0.1.9.dist-info/WHEEL
izi_pygame-0.1.9.dist-info/top_level.txt
