Metadata-Version: 2.1
Name: izi-pygame
Version: 0.1.9
Summary: A small package who's made pygame easier about the drawing rects, the pictures, the fonts and the windows. You have to install pygame. To import write: import izi_pygame In the 0.1.9 version -> add Fontstring object (work with Printstring)! Call izi_pygame.doc() the github of the project will open. dowload project and open /doc/index.html with your browser. A DOCUMENTATION is also available on my github (the same as izi_pygame.doc()), read it if you want to understand the role of this p
Home-page: https://github.com/DaveTilheim/izi-pygame
Author: Dave Tilheim
Author-email: mb624967@skynet.be
License: UNKNOWN
Platform: UNKNOWN
Classifier: Programming Language :: Python :: 3.6
Classifier: License :: OSI Approved :: MIT License
